insta360/rtmp/__init__.py
insta360/rtmp/events.py
insta360/rtmp/exception.py
insta360/rtmp/model.py
insta360/rtmp/rtmp.py
insta360/rtmp/utils.py
insta360/utils/utilities.py
insta360/utils/video.py
insta360-0.1.12.dist-info/METADATA
insta360-0.1.12.dist-info/WHEEL
insta360-0.1.12.dist-info/licenses/LICENSE
insta360-0.1.12.dist-info/RECORD
